{"stats":{"minecraft:picked_up":{"minecraft:powered_rail":22},"minecraft:custom":{"minecraft:time_since_rest":13901,"minecraft:crouch_one_cm":677,"minecraft:play_time":13901,"minecraft:sprint_one_cm":3413,"minecraft:walk_one_cm":10703,"minecraft:sneak_time":469,"minecraft:drop":2,"minecraft:jump":38,"minecraft:minecart_one_cm":18031,"minecraft:leave_game":1,"minecraft:time_since_death":13901,"minecraft:total_world_time":14713,"minecraft:fly_one_cm":73347},"minecraft:used":{"minecraft:lever":7,"minecraft:repeater":6,"minecraft:rail":7,"minecraft:redstone":25,"minecraft:grass_block":18,"minecraft:powered_rail":82,"minecraft:minecart":5,"minecraft:redstone_block":79,"minecraft:observer":11},"minecraft:dropped":{"minecraft:detector_rail":1,"minecraft:rail":1}},"DataVersion":4058}